{
    "test1" :[
       { "label": "T1 Door stretch", "duration": 30 },
       { "label": "Wall stand", "duration": 20 }
    ],
    "test2" :[
        { "label": "T2 Door stretch", "duration": 30 },
        { "label": "Wall stand", "duration": 20 }
    ],
    "test3" :[
        { "label": "T3 Door stretch", "duration": 30 },
        { "label": "Wall stand", "duration": 20 }
    ],
    "Nina's Exercises" :[
        { "label": "Balance on ball, first time ", "duration": 60 },
        { "label": "Balance on ball, second time ", "duration": 60 },
        { "label": "Balance on ball, final time ", "duration": 60 },
        { "label": "Wall stand, first", "duration": 30 },
        { "label": "Wall stand, second", "duration": 30 },
        { "label": "Wall stand, third", "duration": 30 },
        { "label": "Wall stand, fourth", "duration": 30 },
        { "label": "Wall stand, final", "duration": 30 },
        { "label": "Back stretch, first time", "duration": 30 },
        { "label": "Back stretch, second time", "duration": 30 },
        { "label": "Back stretch, third time", "duration": 30 },
        { "label": "Back stretch, fourth time", "duration": 30 },
        { "label": "Back stretch, final time", "duration": 30 },
        { "label": "Walk out to the garage for next exercises", "duration": 120 },
        { "label": "Row exercise, first time", "duration": 30 },
        { "label": "Row exercise, second time", "duration": 30 },
        { "label": "Row exercise, final time", "duration": 30 }
    ],
    "Robert's Exercises" : [
        { "label": "Door stretch", "duration": 60 },
        { "label": "Wall stand", "duration": 60 },
        { "label": "Door stretch", "duration": 60 },
        { "label": "Wall stand", "duration": 60 },
        { "label": "Door stretch", "duration": 60 },
        { "label": "Wall stand", "duration": 60 },
        { "label": "Touch toes", "duration": 40 },
        { "label": "Wall sit", "duration": 40 },
        { "label": "Tricep dips", "duration": 40 },
        { "label": "Lunges", "duration": 40 },
        { "label": "Push-ups", "duration": 40 },
        { "label": "Crunches", "duration": 40 },
        { "label": "Reverse plank", "duration": 40 },
        { "label": "Crouching dog", "duration": 40 },
        { "label": "Calf raises", "duration": 40 },
        { "label": "Hand to wall", "duration": 40 },
        { "label": "Plank", "duration": 40 },
        { "label": "T-raises", "duration": 40 },
        { "label": "Butt lift", "duration": 40 },
        { "label": "Push-ups", "duration": 40 },
        { "label": "Arm circles", "duration": 40 },
        { "label": "Touch toes", "duration": 40 }
    ],
    "bren" : [
        { "label": "Door stretch", "duration": 30 },
        { "label": "Wall stand", "duration": 60 },
        { "label": "Door stretch", "duration": 20 },
        { "label": "Wall stand", "duration": 60 },
        { "label": "Door stretch", "duration": 60 },
        { "label": "Wall stand", "duration": 60 },
        { "label": "Touch toes", "duration": 40 },
        { "label": "Wall sit", "duration": 40 },
        { "label": "Tricep dips", "duration": 40 },
        { "label": "Lunges", "duration": 40 },
        { "label": "Push-ups", "duration": 40 },
        { "label": "Crunches", "duration": 40 },
        { "label": "Reverse plank", "duration": 40 },
        { "label": "Crouching dog", "duration": 40 },
        { "label": "Calf raises", "duration": 40 },
        { "label": "Hand to wall", "duration": 40 },
        { "label": "Plank", "duration": 40 },
        { "label": "T-raises", "duration": 40 },
        { "label": "Butt lift", "duration": 40 },
        { "label": "Push-ups", "duration": 40 },
        { "label": "Arm circles", "duration": 40 },
        { "label": "Touch toes", "duration": 40 }
        ]
}
